odoo/addons/edi_exchange_template_party_data/README.rst
odoo/addons/edi_exchange_template_party_data/__init__.py
odoo/addons/edi_exchange_template_party_data/__manifest__.py
odoo/addons/edi_exchange_template_party_data/i18n/edi_exchange_template_party_data.pot
odoo/addons/edi_exchange_template_party_data/models/__init__.py
odoo/addons/edi_exchange_template_party_data/models/edi_exchange_template_output.py
odoo/addons/edi_exchange_template_party_data/readme/CONTRIBUTORS.rst
odoo/addons/edi_exchange_template_party_data/readme/DESCRIPTION.rst
odoo/addons/edi_exchange_template_party_data/static/description/icon.png
odoo/addons/edi_exchange_template_party_data/static/description/index.html
odoo/addons/edi_exchange_template_party_data/tests/__init__.py
odoo/addons/edi_exchange_template_party_data/tests/test_output_tmpl.py
odoo14_addon_edi_exchange_template_party_data-14.0.1.0.1.dist-info/METADATA
odoo14_addon_edi_exchange_template_party_data-14.0.1.0.1.dist-info/WHEEL
odoo14_addon_edi_exchange_template_party_data-14.0.1.0.1.dist-info/top_level.txt
odoo14_addon_edi_exchange_template_party_data-14.0.1.0.1.dist-info/RECORD
