Metadata-Version: 2.1
Name: odoo14-addon-edi-exchange-template-party-data
Version: 14.0.1.0.1
Summary: Glue module betweeb edi_exchange_template and edi_party_data
Home-page: https://github.com/OCA/edi
Author: Camptocamp,Odoo Community Association (OCA)
Author-email: support@odoo-community.org
License: AGPL-3
Platform: UNKNOWN
Classifier: Programming Language :: Python
Classifier: Framework :: Odoo
Classifier: Framework :: Odoo :: 14.0
Classifier: License :: OSI Approved :: GNU Affero General Public License v3
Classifier: Development Status :: 3 - Alpha
Requires-Python: >=3.6
Requires-Dist: odoo14-addon-edi-exchange-template-oca
Requires-Dist: odoo14-addon-edi-party-data-oca
Requires-Dist: odoo (<14.1dev,>=14.0a)
